layer/__init__.py
layer/auth.py
layer/cache/__init__.py
layer/cache/cache.py
layer/cache/utils.py
layer/clients/__init__.py
layer/clients/account_service.py
layer/clients/data_catalog.py
layer/clients/dataset_service.py
layer/clients/executor_service.py
layer/clients/flow_manager.py
layer/clients/label.py
layer/clients/layer.py
layer/clients/logged_data_service.py
layer/clients/model_catalog.py
layer/clients/project_service.py
layer/clients/protomappers/__init__.py
layer/clients/protomappers/aws.py
layer/clients/protomappers/datasets.py
layer/clients/protomappers/models.py
layer/clients/protomappers/projects.py
layer/clients/protomappers/runs.py
layer/clients/run_service.py
layer/clients/user_logs_service.py
layer/cloudpickle/LICENSE
layer/cloudpickle/__init__.py
layer/cloudpickle/cloudpickle.py
layer/cloudpickle/cloudpickle_fast.py
layer/cloudpickle/compat.py
layer/config/__init__.py
layer/config/config.py
layer/config/config_client.py
layer/config/config_manager.py
layer/config/guest_login_client.py
layer/context.py
layer/contracts/__init__.py
layer/contracts/accounts.py
layer/contracts/assertions.py
layer/contracts/asset.py
layer/contracts/aws.py
layer/contracts/conda.py
layer/contracts/datasets.py
layer/contracts/definitions.py
layer/contracts/fabrics.py
layer/contracts/logged_data.py
layer/contracts/models.py
layer/contracts/project_full_name.py
layer/contracts/projects.py
layer/contracts/remote_runs.py
layer/contracts/resources.py
layer/contracts/runs.py
layer/contracts/tracker.py
layer/decorators/__init__.py
layer/decorators/assertions.py
layer/decorators/conda_decorator.py
layer/decorators/dataset_decorator.py
layer/decorators/fabric_decorator.py
layer/decorators/layer_wrapper.py
layer/decorators/model_decorator.py
layer/decorators/pip_requirements_decorator.py
layer/decorators/resources_decorator.py
layer/decorators/settings.py
layer/exceptions/__init__.py
layer/exceptions/exceptions.py
layer/exceptions/status_report.py
layer/executables/__init__.py
layer-0.10.3150493728.dist-info/LICENSE
layer-0.10.3150493728.dist-info/WHEEL
layer-0.10.3150493728.dist-info/METADATA
layer-0.10.3150493728.dist-info/RECORD
