Metadata-Version: 2.1
Name: layer
Version: 0.10.3150493728
Summary: Layer AI SDK
Home-page: https://layer.ai
License: Apache-2.0
Keywords: MLOps,ML Experiment Tracking,ML Model Registry,ML Model Store,ML Metadata Store
Author: Layer
Author-email: info@layer.ai
Requires-Python: >=3.7.1,<3.11
Classifier: Development Status :: 4 - Beta
Classifier: Environment :: Console
Classifier: Intended Audience :: Developers
Classifier: Intended Audience :: Science/Research
Classifier: License :: OSI Approved :: Apache Software License
Classifier: Natural Language :: English
Classifier: Operating System :: MacOS
Classifier: Operating System :: Microsoft :: Windows
Classifier: Operating System :: POSIX
Classifier: Operating System :: Unix
Classifier: Programming Language :: Python :: 3
Classifier: Programming Language :: Python :: 3.8
Classifier: Programming Language :: Python :: 3.9
Classifier: Programming Language :: Python :: 3.10
Classifier: Programming Language :: Python :: 3
Classifier: Programming Language :: Python :: 3.10
Classifier: Programming Language :: Python :: 3.11
Classifier: Programming Language :: Python :: 3.7
Classifier: Programming Language :: Python :: 3.8
Classifier: Programming Language :: Python :: 3.9
Classifier: Programming Language :: Python :: Implementation :: CPython
Classifier: Topic :: Scientific/Engineering :: Artificial Intelligence
Classifier: Topic :: Software Development :: Libraries :: Python Modules
Classifier: Topic :: System :: Logging
Classifier: Topic :: System :: Monitoring
Requires-Dist: Jinja2
Requires-Dist: aiohttp (>=3.7.3,<3.8.0)
Requires-Dist: boto3 (>=1.16.24)
Requires-Dist: cryptography (>=3.4.7)
Requires-Dist: humanize (>=3.11.0)
Requires-Dist: layer-api (==0.9.384528)
Requires-Dist: lazy_loader (==0.1rc3)
Requires-Dist: mlflow-skinny (>=1.25.0)
Requires-Dist: networkx (>=2.5)
Requires-Dist: numpy (<1.22); python_version >= "3.7" and python_version < "3.8"
Requires-Dist: nvsmi (>=0.4.2,<0.5.0)
Requires-Dist: pandas (==1.3.5)
Requires-Dist: polling (>=0.3.1)
Requires-Dist: psutil (>=5.4.8)
Requires-Dist: pyarrow (==9.0.0)
Requires-Dist: pyjwt (>=2.0.0,<3.0.0)
Requires-Dist: requests (>=2.23.0)
Requires-Dist: rich (>=11)
Requires-Dist: wrapt (>=1.13.3)
Requires-Dist: yarl (>=1.6.3)
Project-URL: Bug Tracker, https://github.com/layerai/sdk/issues
Project-URL: Documentation, https://docs.layer.ai/
Project-URL: Repository, https://github.com/layerai/sdk
